{"huddy987":"neutral","AppemanxD":"neutral","BaseballRJP":"neutral","Gusdl":"approve","uli6969":"deny","Shizrah":"neutral","stolennn1":"deny","thcthsc":"neutral","dunzeod":"neutral","GymShowers":"deny","Addward":"approve","applep13":"neutral","BrastaSauce":"deny","teamfailz":"deny","azalea_k":"approve","Svenskaren":"deny","GreatMemes":"neutral","boelicious":"approve","Mr-B0j4ngl3s":"approve","mustard-man":"neutral","Malfane33":"neutral","_Hybridz":"approve","_CookieBandit":"deny","Genericamel":"neutral","InclementDeath":"approve","beef_nib":"neutral","mlgloaf":"neutral","ZanezzLoL":"deny","GreenDoomsDay":"approve","luciferrukin":"neutral","Draulon":"neutral","nisk0":"neutral","partyboy690":"deny","georgeoj":"neutral","Captain_Ozone":"neutral","TheBCG616":"neutral","k1d89":"deny","DignitasMichael":"neutral","GoldLobster":"approve","Reizh":"deny","Thefatheroftheabyss":"approve","JDilleen":"neutral","Elwyn123":"neutral","Galicizer":"deny","Serunder":"neutral","CoolBlackGuy7":"deny","never_cleaned_comp":"neutral","TheGenericBanana":"approve","Jpon9":"approve","TehStuzz":"approve","097aceofspades":"deny","DanBergundy":"neutral","link5505":"deny","NightGore":"neutral","ZezurgeMC":"neutral","Ghostiieee":"approve","CheesyHotDogPuff":"deny","sidipi":"approve","trenton_jeffro":"deny","aiiX23":"neutral","c4bb0ose":"neutral","deadcandancena":"deny","ehe9501":"deny","pete2fiddy":"approve","ZionTheKing":"neutral","Tip-":"neutral"}